xortool_ciphey/__init__.py
xortool_ciphey/args.py
xortool_ciphey/charset.py
xortool_ciphey/colors.py
xortool_ciphey/libcolors.py
xortool_ciphey/routine.py
xortool_ciphey/tool_main.py
xortool_ciphey/tool_xor.py
xortool_ciphey-0.1.16.dist-info/WHEEL
xortool_ciphey-0.1.16.dist-info/METADATA
xortool_ciphey-0.1.16.dist-info/RECORD
