Metadata-Version: 2.1
Name: xortool-ciphey
Version: 0.1.16
Summary: Multi-byte xor analysis for Ciphey
License: MIT
Author: bee-san
Author-email: github@skerritt.blog
Requires-Python: >=3.4,<4.0
Classifier: License :: OSI Approved :: MIT License
Classifier: Programming Language :: Python :: 3
Classifier: Programming Language :: Python :: 3.4
Classifier: Programming Language :: Python :: 3.5
Classifier: Programming Language :: Python :: 3.6
Classifier: Programming Language :: Python :: 3.7
Classifier: Programming Language :: Python :: 3.8
Classifier: Programming Language :: Python :: 3.9
